paddleslim/__init__.py
paddleslim/analysis/__init__.py
paddleslim/analysis/_utils.py
paddleslim/analysis/extract_features.py
paddleslim/analysis/flops.py
paddleslim/analysis/latency.py
paddleslim/analysis/latency_predictor.py
paddleslim/analysis/model_size.py
paddleslim/analysis/parse_ops.py
paddleslim/auto_compression/__init__.py
paddleslim/auto_compression/analysis.py
paddleslim/auto_compression/auto_strategy.py
paddleslim/auto_compression/compressor.py
paddleslim/auto_compression/config_helpers.py
paddleslim/auto_compression/create_compressed_program.py
paddleslim/auto_compression/strategy_config.py
paddleslim/auto_compression/transformer_pruner.py
paddleslim/auto_compression/utils/__init__.py
paddleslim/auto_compression/utils/fake_ptq.py
paddleslim/auto_compression/utils/predict.py
paddleslim/auto_compression/utils/prune_model.py
paddleslim/common/__init__.py
paddleslim/common/analyze_helper.py
paddleslim/common/cached_reader.py
paddleslim/common/client.py
paddleslim/common/config_helper.py
paddleslim/common/controller.py
paddleslim/common/controller_client.py
paddleslim/common/controller_server.py
paddleslim/common/dataloader.py
paddleslim/common/load_model.py
paddleslim/common/lock.py
paddleslim/common/log_helper.py
paddleslim/common/meter.py
paddleslim/common/patterns.py
paddleslim/common/patterns_common.py
paddleslim/common/recover_program.py
paddleslim/common/sa_controller.py
paddleslim/common/server.py
paddleslim/common/transformer_pattern.py
paddleslim/common/wrapper_function.py
paddleslim/common/rl_controller/__init__.py
paddleslim/common/rl_controller/base_env.py
paddleslim/common/rl_controller/utils.py
paddleslim/common/rl_controller/lstm/__init__.py
paddleslim/common/rl_controller/lstm/lstm_controller.py
paddleslim/core/__init__.py
paddleslim/core/dygraph.py
paddleslim/core/graph.py
paddleslim/core/graph_tracer.py
paddleslim/core/graph_wrapper.py
paddleslim/core/registry.py
paddleslim/dist/__init__.py
paddleslim/dist/dml.py
paddleslim-2.6.0.dist-info/LICENSE
paddleslim-2.6.0.dist-info/METADATA
paddleslim-2.6.0.dist-info/WHEEL
paddleslim-2.6.0.dist-info/top_level.txt
paddleslim-2.6.0.dist-info/RECORD
