Metadata-Version: 2.1
Name: paddleslim
Version: 2.6.0
Summary: A toolkit for generating small model.
Home-page: http://gitlab.baidu.com/PaddlePaddle/PaddleSlim
Author: PaddlePaddle Author
Author-email: dltp-all@baidu.com
License: Apache 2.0
Keywords: PaddleSlim paddlepaddle model-optimize compression
Platform: UNKNOWN
Classifier: Development Status :: 4 - Beta
Classifier: Intended Audience :: Developers
Classifier: Intended Audience :: Education
Classifier: Intended Audience :: Science/Research
Classifier: License :: OSI Approved :: Apache Software License
Classifier: Programming Language :: Python :: 2.7
Classifier: Programming Language :: Python :: 3
Classifier: Programming Language :: Python :: 3.4
Classifier: Programming Language :: Python :: 3.5
Classifier: Programming Language :: Python :: 3.6
Classifier: Topic :: Scientific/Engineering
Classifier: Topic :: Scientific/Engineering :: Mathematics
Classifier: Topic :: Scientific/Engineering :: Artificial Intelligence
Classifier: Topic :: Software Development
Classifier: Topic :: Software Development :: Libraries
Classifier: Topic :: Software Development :: Libraries :: Python Modules
Requires-Dist: tqdm
Requires-Dist: pyzmq
Requires-Dist: matplotlib
Requires-Dist: pillow
Requires-Dist: pyyaml
Requires-Dist: scikit-learn
Requires-Dist: swig
Requires-Dist: opencv-python (==4.6.0.66)
